prevalidate/__init__.py
prevalidate/__main__.py
prevalidate/main.py
prevalidate/sentinel/__init__.py
prevalidate/sentinel/detections.py
prevalidate/sentinel/libs/Kusto.Language.dll
prevalidate/sentinel/main.py
prevalidate/sentinel/models/__init__.py
prevalidate/sentinel/models/detection.py
prevalidate/sentinel/plugins.py
prevalidate/sentinel/templates/detection.md
prevalidate/sentinel/test_stages/test_sentinel.py
prevalidate/sentinel/workspace.py
prevalidate-0.0.1.dist-info/LICENSE
prevalidate-0.0.1.dist-info/METADATA
prevalidate-0.0.1.dist-info/WHEEL
prevalidate-0.0.1.dist-info/entry_points.txt
prevalidate-0.0.1.dist-info/RECORD
